LICENSE.txt
pyproject.toml
setup.py
conet/__init__.py
conet/reach.py
conet.egg-info/PKG-INFO
conet.egg-info/SOURCES.txt
conet.egg-info/dependency_links.txt
conet.egg-info/requires.txt
conet.egg-info/top_level.txt
conet/embedding/alias.py
conet/embedding/graph.py
conet/embedding/learn.py
conet/embedding/node2vec.py
conet/labels/metrics.py
conet/labels/propagatelabels.py
conet/labels/propagators/directed.py
conet/labels/propagators/undirected.py
conet/utils/exceptions.py